ads4MO/__init__.py
ads4MO-0.0.5.dist-info/LICENSE
ads4MO-0.0.5.dist-info/METADATA
ads4MO-0.0.5.dist-info/WHEEL
ads4MO-0.0.5.dist-info/top_level.txt
ads4MO-0.0.5.dist-info/RECORD
