Metadata-Version: 2.1
Name: ads4MO
Version: 0.0.5
Summary: Python module which adds new CMEMS downloads services (applied mainly to big data requests)
Home-page: https://github.com/carmelosammarco/ads4MO
Author: Carmelo Sammarco
Author-email: sammarcocarmelo@gmail.com
License: gpl-3.0
Platform: UNKNOWN
Classifier: Development Status :: 3 - Alpha
Classifier: Intended Audience :: Science/Research
Classifier: Topic :: Scientific/Engineering
Classifier: Programming Language :: Python :: 3.6
Requires-Python: ~=3.6
Requires-Dist: motuclient (>=1.8.1)
Requires-Dist: ftputil (>=3.4)
